lofter_utils/CmdInterface.py
lofter_utils/TagConverter.py
lofter_utils/TagConverterHelper.py
lofter_utils/TagDownloadHelper.py
lofter_utils/TagDownloader.py
lofter_utils/__init__.py
lofter_utils-0.1.4.dist-info/LICENSE
lofter_utils-0.1.4.dist-info/METADATA
lofter_utils-0.1.4.dist-info/WHEEL
lofter_utils-0.1.4.dist-info/entry_points.txt
lofter_utils-0.1.4.dist-info/top_level.txt
lofter_utils-0.1.4.dist-info/RECORD
