Metadata-Version: 2.1
Name: lofter-utils
Version: 0.1.4
Summary: Lofter utils support download and convert danmu.
Home-page: https://github.com/Hawthorn2013/lofter_utils
Author: Hawthorn2013
Author-email: hawthorn7dd@hotmail.com
License: UNKNOWN
Platform: UNKNOWN
Classifier: Programming Language :: Python :: 3
Classifier: License :: OSI Approved :: MIT License
Classifier: Operating System :: OS Independent
